pancho/__init__.py
pancho/aux/__init__.py
pancho/aux/wrappers.py
pancho/definition/__init__.py
pancho/definition/contracts.py
pancho/definition/exceptions.py
pancho/implementation/__init__.py
pancho/implementation/execution.py
pancho/implementation/processing.py
pancho/implementation/registry.py
pancho/implementation/transformers.py
pancho-1.4.0.dist-info/LICENSE
pancho-1.4.0.dist-info/METADATA
pancho-1.4.0.dist-info/WHEEL
pancho-1.4.0.dist-info/RECORD
