Metadata-Version: 2.1
Name: pancho
Version: 1.4.0
Summary: Commands and queries processor
Home-page: https://github.com/smairon/pancho
Author: Smairon
Author-email: man@smairon.ru
Requires-Python: >=3.11,<4.0
Classifier: Programming Language :: Python :: 3
Classifier: Programming Language :: Python :: 3.11
Classifier: Programming Language :: Python :: 3.12
Requires-Dist: pytest-asyncio (>=1.0.0,<2.0.0)
Requires-Dist: zodchy (>=0.5.3,<0.6.0)
Project-URL: Repository, https://github.com/smairon/pancho
